[{"name":"Sheikh Tahmeed Hossain","e-mail":"tahmeedhossain99@gmail.com","username":"antor","gender":"male","dateofbirth":"1998-12-09","password":"dvgsdvsdvd","confirmpassword":"dvgsdvsdvd"},{"name":"babayaga babayaga","e-mail":"babayaga47@gmail.com","username":"vdv","gender":"male","dateofbirth":"1998-12-14","password":"babayaga47","confirmpassword":"babayaga47"},{"name":"tahreen hossain","e-mail":"anika@gmail,com","username":"skanika","gender":"female","dateofbirth":"1998-12-16","password":"anika","confirmpassword":"anika"},{"name":"jahangir hossain","e-mail":"blackbear6660@outlook.com","username":"yahoobaba","gender":"male","dateofbirth":"1998-12-01","password":"jahangir56","confirmpassword":"jahangir56"}]